lightspeed_x/__init__.py
lightspeed_x/base.py
lightspeed_x/types.py
lightspeed_x-0.1.2.dist-info/METADATA
lightspeed_x-0.1.2.dist-info/WHEEL
lightspeed_x-0.1.2.dist-info/RECORD
