Metadata-Version: 2.1
Name: lightspeed_x
Version: 0.1.2
Summary: This is a simple Python wrapper for the Lightspeed X Series API.
Project-URL: Repository, https://github.com/nilaster/lightspeed_x.git
Author-email: nilaster <nilaster@riseup.net>
License: MIT license
Classifier: Development Status :: 3 - Alpha
Classifier: Intended Audience :: Developers
Classifier: Programming Language :: Python :: 3.8
Classifier: Programming Language :: Python :: 3.9
Classifier: Programming Language :: Python :: 3.10
Classifier: Programming Language :: Python :: 3.11
Requires-Python: >=3.8
Requires-Dist: httpx
